neatplot/__init__.py
neatplot/matplotlibrc
neatplot/matplotlibrc_fonts
neatplot-0.1.0.dist-info/METADATA
neatplot-0.1.0.dist-info/WHEEL
neatplot-0.1.0.dist-info/licenses/LICENSE
neatplot-0.1.0.dist-info/RECORD
