Metadata-Version: 2.3
Name: neatplot
Version: 0.1.0
Summary: Plotting utilities for Python
Project-URL: Homepage, https://github.com/willieneis/neatplot
Author: Viraj Mehta
Author-email: Willie Neiswanger <willie.neiswanger@gmail.com>
License-File: LICENSE
Classifier: License :: OSI Approved :: MIT License
Classifier: Operating System :: OS Independent
Classifier: Programming Language :: Python :: 3
Requires-Python: >=3.6
Requires-Dist: matplotlib>=3.2.2
Requires-Dist: numpy>=1.19.0
